__init__.py
bioscape_tools.py
bioscape_tools-1.0.1.dist-info/licenses/LICENSE
bioscape_tools-1.0.1.dist-info/METADATA
bioscape_tools-1.0.1.dist-info/WHEEL
bioscape_tools-1.0.1.dist-info/top_level.txt
bioscape_tools-1.0.1.dist-info/RECORD
