Metadata-Version: 2.4
Name: bioscape_tools
Version: 1.0.1
Summary: Bioscape Tools contains code to make interacting with Bioscape data easier for users
Author-email: Evan Lang <evan.d.lang@nasa.gov>
Maintainer-email: Evan Lang <evan.d.lang@nasa.gov>
License: Apache-2.0
Project-URL: bugs, https://github.com/evandlang/bioscape_tools/issues
Project-URL: homepage, https://github.com/evandlang/bioscape_tools
License-File: LICENSE
Requires-Dist: earthaccess
Requires-Dist: xarray
Requires-Dist: geopandas
Requires-Dist: numpy
Requires-Dist: matplotlib
Provides-Extra: dev
Requires-Dist: coverage; extra == "dev"
Requires-Dist: pytest; extra == "dev"
Dynamic: license-file
